README.rst
setup.py
kuroko/__init__.py
kuroko/_version.py
kuroko/bot.py
kuroko.egg-info/PKG-INFO
kuroko.egg-info/SOURCES.txt
kuroko.egg-info/dependency_links.txt
kuroko.egg-info/not-zip-safe
kuroko.egg-info/requires.txt
kuroko.egg-info/top_level.txt
test/test_kuroko.py