Metadata-Version: 1.1
Name: kuroko
Version: 0.1.7
Summary: Minimalistic Python Bot Framework
Home-page: https://github.com/hhatto/kuroko
Author: Hideo Hattori
Author-email: hhatto.jp@gmail.com
License: MIT License
Keywords: bot framework
Platform: UNKNOWN
Classifier: Development Status :: 3 - Alpha
Classifier: Intended Audience :: Developers
Classifier: Operating System :: Unix
Classifier: Programming Language :: Python
Classifier: Programming Language :: Python :: 2
Classifier: Programming Language :: Python :: 3
